variants/__init__.py
variants/_variants.py
variants/_version.py
variants/inspect.py
variants-0.2.0.dist-info/METADATA
variants-0.2.0.dist-info/RECORD
variants-0.2.0.dist-info/WHEEL
variants-0.2.0.dist-info/top_level.txt
variants-0.2.0.dist-info/zip-safe
