Metadata-Version: 1.2
Name: variants
Version: 0.2.0
Summary: Library that enables the creation of alternate constructor-likevariant forms for arbitrary functions.
Home-page: https://github.com/python-variants/variants
Author: Paul Ganssle
Author-email: paul@ganssle.io
License: Apache Software License 2.0
Keywords: variants
Platform: UNKNOWN
Classifier: Development Status :: 3 - Alpha
Classifier: Intended Audience :: Developers
Classifier: License :: OSI Approved :: Apache Software License
Classifier: Natural Language :: English
Classifier: Programming Language :: Python :: 2
Classifier: Programming Language :: Python :: 2.7
Classifier: Programming Language :: Python :: 3
Classifier: Programming Language :: Python :: 3.4
Classifier: Programming Language :: Python :: 3.5
Classifier: Programming Language :: Python :: 3.6
Requires-Python: >=2.7, !=3.0.*, !=3.1.*, !=3.2.*
